phaistos/__init__.py
phaistos/compiler.py
phaistos/compiler.pyi
phaistos/consts.py
phaistos/consts.pyi
phaistos/exceptions.py
phaistos/exceptions.pyi
phaistos/manager.py
phaistos/manager.pyi
phaistos/py.typed
phaistos/schema.py
phaistos/schema.pyi
phaistos/sources.py
phaistos/sources.pyi
phaistos/transpiler.py
phaistos/transpiler.pyi
phaistos/typings.py
phaistos/typings.pyi
phaistos/utils.py
phaistos/utils.pyi
phaistos-0.2.3.dist-info/LICENSE
phaistos-0.2.3.dist-info/METADATA
phaistos-0.2.3.dist-info/WHEEL
phaistos-0.2.3.dist-info/top_level.txt
phaistos-0.2.3.dist-info/RECORD
