Metadata-Version: 2.1
Name: phaistos
Version: 0.2.3
Summary: Tooling to automatically generate validated data models from YAML configuration files
Home-page: https://phaistos.readthedocs.io/en/latest
Author: Kamil Rybacki
Author-email: kamilandrzejrybacki@gmail.com
License-File: LICENSE
Requires-Dist: PyYAML ==6.0.1
Requires-Dist: pydantic ==2.7.0
